msteamsapi/__init__.py
msteamsapi/adaptive_card.py
msteamsapi/container.py
msteamsapi/enums.py
msteamsapi/webhook.py
msteamsapi-0.9.4.dist-info/LICENSE
msteamsapi-0.9.4.dist-info/METADATA
msteamsapi-0.9.4.dist-info/WHEEL
msteamsapi-0.9.4.dist-info/RECORD
