Metadata-Version: 2.3
Name: msteamsapi
Version: 0.9.4
Summary: Microsoft Teams AdaptiveCards API Wrapper for Python 2 and 3
Author: Alexey Rubasheff
Author-email: alexey.rubasheff@gmail.com
Requires-Python: >=2.7, !=3.0.*, !=3.1.*, !=3.2.*, !=3.3.*, !=3.4.*, !=3.5.*, !=3.6.*, !=3.7.*, !=3.8.*
Classifier: Development Status :: 4 - Beta
Classifier: Intended Audience :: Developers
Classifier: License :: OSI Approved :: MIT License
Classifier: Programming Language :: Python :: 2
Classifier: Programming Language :: Python :: 3
Classifier: Programming Language :: Python :: 3.9
Classifier: Programming Language :: Python :: 3.10
Classifier: Programming Language :: Python :: 3.11
Classifier: Programming Language :: Python :: 3.12
Classifier: Programming Language :: Python :: 3.13
Classifier: Programming Language :: Python :: 2.7
Classifier: Programming Language :: Python :: 3.14
Requires-Dist: enum34 (==1.1.10) ; python_version < "3"
Requires-Dist: future (==1.0.0) ; python_version < "3"
Requires-Dist: importlib-resources (==3.3.1) ; python_version < "3"
Requires-Dist: importlib-resources (>=6.4.0,<7.0.0) ; python_full_version > "3.0.0"
Requires-Dist: pathlib (==1.0.1) ; python_version < "3"
Requires-Dist: requests (==2.27.1) ; python_version < "3"
Requires-Dist: requests (>=2.32.3,<3.0.0) ; python_full_version > "3.0.0"
Project-URL: Repository, https://github.com/ALERTua/msteamsapi
